{
  "city_slug": "oklahoma-city-ok",
  "city": "Oklahoma City",
  "state": "OK",
  "vertical": "pi",
  "sponsor": {
    "status": "inactive"
  },
  "listings": [
    {
      "city_slug": "oklahoma-city-ok",
      "name": "Abel Law Firm",
      "practice_areas": [
        "personal-injury"
      ]
    },
    {
      "city_slug": "oklahoma-city-ok",
      "name": "Cunningham & Mears",
      "practice_areas": [
        "personal-injury"
      ]
    },
    {
      "city_slug": "oklahoma-city-ok",
      "name": "Hasbrook & Hasbrook",
      "practice_areas": [
        "personal-injury"
      ]
    },
    {
      "city_slug": "oklahoma-city-ok",
      "name": "Head Law Firm",
      "practice_areas": [
        "personal-injury"
      ]
    },
    {
      "city_slug": "oklahoma-city-ok",
      "name": "McIntyre Law",
      "practice_areas": [
        "personal-injury"
      ]
    },
    {
      "city_slug": "oklahoma-city-ok",
      "name": "Oklahoma Injury Law Firm",
      "practice_areas": [
        "personal-injury"
      ]
    },
    {
      "city_slug": "oklahoma-city-ok",
      "name": "Rasor Law Firm",
      "practice_areas": [
        "personal-injury"
      ]
    },
    {
      "city_slug": "oklahoma-city-ok",
      "name": "The Carr Law Firm",
      "practice_areas": [
        "personal-injury"
      ]
    }
  ]
}
